QuantResearch/__init__.py
QuantResearch/indicators.py
QuantResearch/visualize.py
quantresearch-0.0.1.dist-info/licenses/LICENSE
quantresearch-0.0.1.dist-info/METADATA
quantresearch-0.0.1.dist-info/WHEEL
quantresearch-0.0.1.dist-info/top_level.txt
quantresearch-0.0.1.dist-info/RECORD
