Metadata-Version: 2.4
Name: QuantResearch
Version: 0.0.1
Summary: Technical indicators and visualization tools for quantitative research
Home-page: https://github.com/vinayak1729-web/QuantR
Author: Vinayak Shinde
Author-email: Vinayak Shinde <vinayak.r.shinde.1729@gmail.com>
License: MIT
Project-URL: Homepage, https://github.com/vinayak1729-web/QuantR
Project-URL: Repository, https://github.com/vinayak1729-web/QuantR
Project-URL: Issues, https://github.com/vinayak1729-web/QuantR/issues
Project-URL: Documentation, https://github.com/vinayak1729-web/QuantR#readme
Keywords: finance,trading,technical-analysis,indicators,quantitative
Classifier: Development Status :: 3 - Alpha
Classifier: Intended Audience :: Developers
Classifier: Intended Audience :: Financial and Insurance Industry
Classifier: Topic :: Office/Business :: Financial :: Investment
Classifier: Programming Language :: Python :: 3
Classifier: Programming Language :: Python :: 3.7
Classifier: Programming Language :: Python :: 3.8
Classifier: Programming Language :: Python :: 3.9
Classifier: Programming Language :: Python :: 3.10
Classifier: Programming Language :: Python :: 3.11
Classifier: License :: OSI Approved :: MIT License
Classifier: Operating System :: OS Independent
Requires-Python: >=3.7
License-File: LICENSE
Requires-Dist: yfinance>=0.2.0
Requires-Dist: pandas>=1.3.0
Requires-Dist: matplotlib>=3.4.0
Provides-Extra: dev
Requires-Dist: pytest>=7.0; extra == "dev"
Requires-Dist: black>=22.0; extra == "dev"
Requires-Dist: flake8>=4.0; extra == "dev"
Requires-Dist: mypy>=0.950; extra == "dev"
Dynamic: author
Dynamic: home-page
Dynamic: license-file
Dynamic: requires-python
